{"name":"Search bar functionality","id":"modal-add-itinerary-search-bar;search-bar-functionality","testSteps":[{"number":1,"description":"When User search top itinerary name \"Danau Toba\"","duration":4,"startTime":"2022-12-12T11:46:24.356795+07:00[Asia/Jakarta]","result":"PENDING","precondition":false,"level":0},{"number":2,"description":"Then Top Itinerary with name \"Danau Toba\" appeared","duration":6,"startTime":"2022-12-12T11:46:24.362181+07:00[Asia/Jakarta]","result":"IGNORED","precondition":false,"level":0}],"userStory":{"id":"modal-add-itinerary-search-bar","storyName":"Modal Add Itinerary Search bar","displayName":"Modal Add Itinerary Search bar","path":"Itinerary/ModalAddItinerary/modal-add-itinterary-search.feature","type":"feature"},"featureTag":{"name":"Modal add itinerary/Modal Add Itinerary Search bar","type":"feature","displayName":"Modal add itinerary/Modal Add Itinerary Search bar"},"title":"Search bar functionality","description":"","backgroundTitle":"User already open Modal Add Itinerary","backgroundDescription":"","tags":[{"name":"Modal add itinerary/Modal Add Itinerary Search bar","type":"feature","displayName":"Modal Add Itinerary Search bar"},{"name":"Itinerary","type":"theme","displayName":"Itinerary"},{"name":"itinerary","type":"tag","displayName":"itinerary"},{"name":"Itinerary/Modal add itinerary","type":"capability","displayName":"Modal add itinerary"}],"startTime":"2022-12-12T11:46:17.702270+07:00[Asia/Jakarta]","duration":31695,"projectKey":"","annotatedResult":"PENDING","isManualTestingUpToDate":false,"manual":false,"testSource":"Cucumber","result":"PENDING"}